ZtjCeleryApi.py
ZtjCeleryApp.py
celery_tools-0.0.1.dist-info/METADATA
celery_tools-0.0.1.dist-info/WHEEL
celery_tools-0.0.1.dist-info/top_level.txt
celery_tools-0.0.1.dist-info/RECORD
