Metadata-Version: 2.1
Name: celery-tools
Version: 0.0.1
Summary: celery tools
Home-page: https://github.com/ztj1993/py-celery-tools
Author: ZhangTianJie
Author-email: ztj1993@gmail.com
License: MIT License
Keywords: fastapi celery
Platform: UNKNOWN
Requires-Dist: fastapi
Requires-Dist: celery
